[
    {
        "id": 1,
        "total": 1748,
        "userId": 2,
        "createAt": 1679869276580,
        "items": [
            {
                "id": 17,
                "quantity": 1,
                "title": "Las tinieblas",
                "author": "Ken Follet",
                "price": "899",
                "stock": "100",
                "category": "Guerra",
                "image": "https://i.ibb.co/60BH4gT/2.jpg"
            },
            {
                "id": 21,
                "quantity": 1,
                "title": "Comer saludable",
                "author": "L. Jimenéz",
                "price": "849",
                "stock": "100",
                "category": "Salud",
                "image": "https://i.ibb.co/4g5xRrr/2.jpg"
            }
        ]
    },
    {
        "id": 2,
        "total": 539,
        "userId": 2,
        "createAt": 1679869276580,
        "items": [
            {
                "id": 25,
                "title": "El cirujano de almas",
                "quantity": 1,
                "author": "Luis Zueco",
                "price": "539",
                "stock": "100",
                "category": "Novela histórica",
                "image": "https://i.ibb.co/r5jJX0z/2.jpg"
            }
        ]
    }
]